<?xml version = '1.0' encoding = 'UTF-8'?>
<Relation class="oracle.dbtools.crest.model.design.logical.Relation" name="Relation_12" directorySegmentName="seg_0" id="8E4CB287-3962-5668-750C-A3728558614B">
<createdBy>eduardo</createdBy>
<createdTime>2020-12-17 06:17:43 UTC</createdTime>
<ownerDesignName>SistemaWeb</ownerDesignName>
<engineerTo>
<item key="B7F93CE7-E585-B276-A831-C128B2571E24" value="true"/>
</engineerTo>
<sourcePk>7051E309-7746-EE64-B366-17E635A41841</sourcePk>
<identifying>false</identifying>
<optionalSource>true</optionalSource>
<optionalTarget>false</optionalTarget>
<sourceCardinality>1</sourceCardinality>
<sourceEntity>C1CF57CC-5698-1DCC-8628-9E0F56054B87</sourceEntity>
<targetCardinalityString>*</targetCardinalityString>
<targetEntity>3BB57B78-2F71-C3E9-DED2-B3EFB6C796BC</targetEntity>
<transferable>true</transferable>
<deleteRule>NO ACTION</deleteRule>
</Relation>
